t3api/__init__.py
t3api/api_client.py
t3api/api_response.py
t3api/configuration.py
t3api/exceptions.py
t3api/py.typed
t3api/rest.py
t3api/api/__init__.py
t3api/api/authentication_api.py
t3api/api/create_package_api.py
t3api/api/create_strains_api.py
t3api/api/create_transfer_api.py
t3api/api/facilities_api.py
t3api/api/free_api.py
t3api/api/harvests_api.py
t3api/api/history_api.py
t3api/api/items_api.py
t3api/api/lab_results_api.py
t3api/api/labels_api.py
t3api/api/licenses_api.py
t3api/api/manifests_api.py
t3api/api/modify_items_api.py
t3api/api/modify_packages_api.py
t3api/api/modify_sales_receipts_api.py
t3api/api/modify_strains_api.py
t3api/api/packages_api.py
t3api/api/pdf_api.py
t3api/api/permissions_api.py
t3api/api/plant_batches_api.py
t3api/api/plants_api.py
t3api/api/reports_api.py
t3api/api/sales_receipts_api.py
t3api/api/search_api.py
t3api/api/single_harvest_api.py
t3api/api/single_item_api.py
t3api/api/single_package_api.py
t3api/api/single_plant_api.py
t3api/api/single_plant_batch_api.py
t3api/api/single_sales_receipt_api.py
t3api/api/single_transfer_api.py
t3api/api/states_api.py
t3api/api/strains_api.py
t3api/api/supercollections_api.py
t3api/api/transfers_api.py
t3api/models/__init__.py
t3api/models/endpoint_id.py
t3api/models/incoming_transfer_manifest_report_response.py
t3api/models/jwt_data.py
t3api/models/lab_testing_states.py
t3api/models/metrc_create_package_inputs_response.py
t3api/models/metrc_create_transfer_inputs_response.py
t3api/models/metrc_credential_auth_payload.py
t3api/models/metrc_delivery_package.py
t3api/models/metrc_delivery_package_list_response.py
t3api/models/metrc_discontinue_item_payload.py
t3api/models/metrc_discontinue_strain_payload.py
t3api/models/metrc_driver.py
t3api/models/metrc_facility.py
t3api/models/metrc_facility_list_response.py
t3api/models/metrc_facility_physical_address.py
t3api/models/metrc_harvest.py
t3api/models/metrc_harvest_list_response.py
t3api/models/metrc_harvest_package.py
t3api-0.5.0.dist-info/licenses/LICENSE
t3api-0.5.0.dist-info/METADATA
t3api-0.5.0.dist-info/WHEEL
t3api-0.5.0.dist-info/top_level.txt
t3api-0.5.0.dist-info/RECORD
