Metadata-Version: 2.4
Name: t3api
Version: 0.5.0
Summary: Python client for the T3 API
Author-email: Matt Frisbie <matt@classvsoftware.com>
License: GPL-3.0-only
Project-URL: Homepage, https://github.com/classvsoftware/t3api-python
Keywords: t3,metrc,api,cannabis,track and trace
Classifier: Development Status :: 3 - Alpha
Classifier: License :: OSI Approved :: GNU General Public License v3 (GPLv3)
Classifier: Programming Language :: Python :: 3
Classifier: Programming Language :: Python :: 3.8
Classifier: Operating System :: OS Independent
Requires-Python: >=3.8
License-File: LICENSE
Requires-Dist: urllib3<3.0.0,>=2.1.0
Requires-Dist: python-dateutil>=2.8.2
Requires-Dist: pydantic>=2
Requires-Dist: typing-extensions>=4.7.1
Dynamic: license-file
